ionos/__init__.py
ionos/dns.py
ionos_dns-0.1.2.dist-info/METADATA
ionos_dns-0.1.2.dist-info/WHEEL
ionos_dns-0.1.2.dist-info/LICENSE
ionos_dns-0.1.2.dist-info/RECORD
