Metadata-Version: 2.1
Name: ionos-dns
Version: 0.1.2
Summary: This contains tools to use the IONOS DNS management API and to perform letsencrypt DNS challenges
Home-page: https://github.com/FredStober/ionos-dns-python
Author: Fred Stober
Author-email: fmail@fredstober.de
Requires-Python: >=3.8,<=3.11
Classifier: Programming Language :: Python :: 3
Classifier: Programming Language :: Python :: 3.8
Classifier: Programming Language :: Python :: 3.9
Classifier: Programming Language :: Python :: 3.10
Classifier: Programming Language :: Python :: 3.11
Requires-Dist: requests (>=2.0)
Project-URL: Documentation, https://FredStober.github.io/ionos-dns-python/
Project-URL: Repository, https://github.com/FredStober/ionos-dns-python
